Adlib/__init__.py
Adlib/analiseDocumentos.py
Adlib/api.py
Adlib/apiConferirRg.py
Adlib/apiValid.py
Adlib/blip.py
Adlib/confirmacao.py
Adlib/criacao.py
Adlib/enums.py
Adlib/exceptions.py
Adlib/fluxguard.py
Adlib/fluxguardTeste.py
Adlib/funcoes.py
Adlib/importacao.py
Adlib/integracao.py
Adlib/libs.py
Adlib/logins.py
Adlib/robos.py
Adlib/utils.py
Adlib/virtaus.py
Adlib/webdriver/chromedriver
Adlib/webdriver/chromedriver.exe
ad_tech-1.0.5.dist-info/licenses/LICENSE
ad_tech-1.0.5.dist-info/METADATA
ad_tech-1.0.5.dist-info/WHEEL
ad_tech-1.0.5.dist-info/top_level.txt
ad_tech-1.0.5.dist-info/RECORD
