Metadata-Version: 2.4
Name: AD-TECH
Version: 1.0.5
Summary: Melhorias para automação web
Home-page: https://github.com/DesenvolvimentoAD/Adlib
Author: Alan, Dannilo, Fabiano e Yan
Author-email: desenvolvimento@adpromotora.com.br
Classifier: Programming Language :: Python :: 3
Classifier: License :: OSI Approved :: MIT License
Classifier: Operating System :: OS Independent
Requires-Python: >=3.6
License-File: LICENSE
Dynamic: author
Dynamic: author-email
Dynamic: classifier
Dynamic: description
Dynamic: description-content-type
Dynamic: home-page
Dynamic: license-file
Dynamic: requires-python
Dynamic: summary
